main.py
mcp_twitterio-0.1.0.dist-info/METADATA
mcp_twitterio-0.1.0.dist-info/WHEEL
mcp_twitterio-0.1.0.dist-info/entry_points.txt
mcp_twitterio-0.1.0.dist-info/top_level.txt
mcp_twitterio-0.1.0.dist-info/RECORD
