Metadata-Version: 2.4
Name: mcp-twitterio
Version: 0.1.0
Summary: Twitter API的MCP服务，基于twitterapi.io，使用studio模式进行通信
Requires-Python: >=3.12
Requires-Dist: httpx>=0.28.1
Requires-Dist: mcp>=1.6.0
Requires-Dist: python-dotenv>=1.0.0
Provides-Extra: dev
Requires-Dist: black>=24.1.0; extra == "dev"
Requires-Dist: isort>=5.12.0; extra == "dev"
Requires-Dist: pytest>=7.4.0; extra == "dev"
